openapi/__init__.py
openapi/main.py
openapi/dto/__init__.py
openapi/dto/account/AccountInformationResponse.py
openapi/dto/account/__init__.py
openapi/dto/account/account_information_response.py
openapi/dto/authen/TokenResponseDto.py
openapi/dto/authen/__init__.py
openapi/dto/authen/token_response_dto.py
openapi/dto/derivative_dto/__init__.py
openapi/dto/derivative_dto/derivative_dto.py
openapi/dto/money/__init__.py
openapi/dto/money/money.py
openapi/dto/stock_normal/__init__.py
openapi/dto/stock_normal/stock_normal_dto.py
openapi/service/__init__.py
openapi/service/account/__init__.py
openapi/service/account/account.py
openapi/service/authen/__init__.py
openapi/service/authen/token.py
openapi/service/derivative/__init__.py
openapi/service/derivative/derivative.py
openapi/service/money/__init__.py
openapi/service/money/money.py
openapi/service/stock_normal/__init__.py
openapi/service/stock_normal/normal.py
openapi/utils/RequestApi.py
openapi/utils/__init__.py
openapi/utils/constant.py
openapi/utils/request_api.py
open_api_tcbs-1.0.0.dist-info/METADATA
open_api_tcbs-1.0.0.dist-info/WHEEL
open_api_tcbs-1.0.0.dist-info/top_level.txt
open_api_tcbs-1.0.0.dist-info/RECORD
