Metadata-Version: 2.1
Name: open-api-tcbs
Version: 1.0.0
Summary: Library connect Open-API of TCBS
Home-page: https://developers.tcbs.com.vn/
Author: hoangdd
Author-email: dangduyhoang3009@gmail.com
Classifier: Programming Language :: Python :: 3
Classifier: License :: OSI Approved :: MIT License
Classifier: Operating System :: OS Independent
Requires-Python: >=3.6
Requires-Dist: appnope ==0.1.4
Requires-Dist: asttokens ==2.4.1
Requires-Dist: attrs ==24.2.0
Requires-Dist: backcall ==0.2.0
Requires-Dist: beautifulsoup4 ==4.12.3
Requires-Dist: bleach ==6.2.0
Requires-Dist: certifi ==2024.8.30
Requires-Dist: charset-normalizer ==3.4.0
Requires-Dist: dacite ==1.8.1
Requires-Dist: dataclasses-json ==0.6.7
Requires-Dist: decorator ==5.1.1
Requires-Dist: defusedxml ==0.7.1
Requires-Dist: docopt ==0.6.2
Requires-Dist: executing ==2.1.0
Requires-Dist: fastjsonschema ==2.20.0
Requires-Dist: from-dict ==0.4.1
Requires-Dist: idna ==3.10
Requires-Dist: importlib-metadata ==8.5.0
Requires-Dist: ipython ==8.12.3
Requires-Dist: jedi ==0.19.1
Requires-Dist: Jinja2 ==3.1.4
Requires-Dist: jsonschema ==4.23.0
Requires-Dist: jsonschema-specifications ==2024.10.1
Requires-Dist: jupyter-client ==8.6.3
Requires-Dist: jupyter-core ==5.7.2
Requires-Dist: jupyterlab-pygments ==0.3.0
Requires-Dist: MarkupSafe ==3.0.2
Requires-Dist: marshmallow ==3.23.0
Requires-Dist: matplotlib-inline ==0.1.7
Requires-Dist: mistune ==3.0.2
Requires-Dist: mypy-extensions ==1.0.0
Requires-Dist: nbclient ==0.10.0
Requires-Dist: nbconvert ==7.16.4
Requires-Dist: nbformat ==5.10.4
Requires-Dist: packaging ==24.1
Requires-Dist: pandocfilters ==1.5.1
Requires-Dist: parso ==0.8.4
Requires-Dist: pexpect ==4.9.0
Requires-Dist: pickleshare ==0.7.5
Requires-Dist: pip-autoremove ==0.10.0
Requires-Dist: pipreqs ==0.5.0
Requires-Dist: platformdirs ==4.3.6
Requires-Dist: prompt-toolkit ==3.0.48
Requires-Dist: ptyprocess ==0.7.0
Requires-Dist: pure-eval ==0.2.3
Requires-Dist: Pygments ==2.18.0
Requires-Dist: python-dateutil ==2.9.0.post0
Requires-Dist: pyzmq ==26.2.0
Requires-Dist: referencing ==0.35.1
Requires-Dist: requests ==2.32.3
Requires-Dist: rpds-py ==0.20.1
Requires-Dist: six ==1.16.0
Requires-Dist: soupsieve ==2.6
Requires-Dist: stack-data ==0.6.3
Requires-Dist: tinycss2 ==1.4.0
Requires-Dist: tornado ==6.4.1
Requires-Dist: traitlets ==5.14.3
Requires-Dist: typing-inspect ==0.9.0
Requires-Dist: typing-extensions ==4.12.2
Requires-Dist: urllib3 ==2.2.3
Requires-Dist: wcwidth ==0.2.13
Requires-Dist: webencodings ==0.5.1
Requires-Dist: yarg ==0.1.9
Requires-Dist: zipp ==3.20.2
